MANIFEST.in
README.md
VERSION
setup.cfg
setup.py
aiohttp_prometheus_monitoring/__init__.py
aiohttp_prometheus_monitoring/exceptions.py
aiohttp_prometheus_monitoring/utils.py
aiohttp_prometheus_monitoring/views.py
aiohttp_prometheus_monitoring.egg-info/PKG-INFO
aiohttp_prometheus_monitoring.egg-info/SOURCES.txt
aiohttp_prometheus_monitoring.egg-info/dependency_links.txt
aiohttp_prometheus_monitoring.egg-info/requires.txt
aiohttp_prometheus_monitoring.egg-info/top_level.txt
aiohttp_prometheus_monitoring/metrics/__init__.py
aiohttp_prometheus_monitoring/metrics/amqp.py
aiohttp_prometheus_monitoring/metrics/base.py
aiohttp_prometheus_monitoring/metrics/http.py
aiohttp_prometheus_monitoring/metrics/mysql.py
aiohttp_prometheus_monitoring/metrics/postgres.py
aiohttp_prometheus_monitoring/metrics/redis.py
example/__init__.py
example/main.py
example/settings.py